[
    {
        "name": "koyuspace",
        "url": "https://koyu.space/api/v1/instance",
        "enabled": true,
        "custom": false
    },
    {
        "name": "cdn",
        "url": "https://f001.backblazeb2.com/file/koyuspace-media/media_attachments/files/108/131/884/963/155/122/original/aa5f35d6a3bf95d2.png",
        "enabled": true,
        "custom": true
    },
    {
        "name": "updates",
        "url": "https://updates.koyu.space",
        "enabled": true,
        "custom": false
    },
    {
        "name": "ghpages",
        "url": "https://blog.koyu.space",
        "enabled": true,
        "custom": false
    },
    {
        "name": "mail",
        "url": "https://mail.koyu.space",
        "enabled": true,
        "custom": true
    },
    {
        "name": "chat",
        "url": "https://chat.koyu.space/api/v1/server_settings",
        "enabled": true,
        "custom": false
    }
]
